imuthes/keepass/__init__.py
imuthes/keepass/cli.py
imuthes/keepass/get.py
imuthes/keepass/keepass.py
imuthes/keepass/server.py
imuthes/keepass/shutdown.py
imuthes_keepass-0.0.0a1.dist-info/METADATA
imuthes_keepass-0.0.0a1.dist-info/WHEEL
imuthes_keepass-0.0.0a1.dist-info/RECORD
