Metadata-Version: 2.3
Name: imuthes-keepass
Version: 0.0.0a1
Summary: Keepass Tools
License: LGPL-3.0-or-later
Author: Bernhard Radermacher
Author-email: bernhard.radermacher@netlink-consulting.com
Requires-Python: >=3.13,<3.14
Classifier: Topic :: Software Development
Classifier: Development Status :: 4 - Beta
Classifier: Intended Audience :: Developers
Classifier: License :: OSI Approved :: GNU Lesser General Public License v3 or later (LGPLv3+)
Classifier: Topic :: Utilities
Requires-Dist: fastapi (>=0.115.11,<0.116.0)
Requires-Dist: imuthes (>=0.0.0a3,<1.4.0)
Requires-Dist: pykeepass (>=4.1.1.post1,<5.0.0)
Requires-Dist: uvicorn (>=0.34.0,<0.35.0)
Project-URL: Repository, https://gitlab.com/imuthes/keepass
